pytest_time/__init__.py
pytest_time/_version.py
pytest_time/fake_time.py
pytest_time/instant_sleep.py
pytest_time/py.typed
pytest_time/real_time.py
pytest_time/wrap_time.py
pytest_time-0.4.1.dist-info/COPYING
pytest_time-0.4.1.dist-info/METADATA
pytest_time-0.4.1.dist-info/WHEEL
pytest_time-0.4.1.dist-info/entry_points.txt
pytest_time-0.4.1.dist-info/top_level.txt
pytest_time-0.4.1.dist-info/RECORD
