Metadata-Version: 2.2
Name: pytest_time
Version: 0.4.1
Project-URL: Documentation, https://pytest-time.readthedocs.io
Project-URL: Repository, https://github.com/lengau/pytest-time
Project-URL: Issues, https://github.com/lengau/pytest-time/issues
Classifier: Development Status :: 3 - Alpha
Classifier: License :: OSI Approved :: GNU Lesser General Public License v3 (LGPLv3)
Classifier: Programming Language :: Python :: 3
Classifier: Programming Language :: Python :: 3.8
Classifier: Programming Language :: Python :: 3.9
Classifier: Programming Language :: Python :: 3.10
Classifier: Programming Language :: Python :: 3.11
Classifier: Programming Language :: Python :: 3.12
Classifier: Programming Language :: Python :: 3.13
Classifier: Framework :: Pytest
Classifier: Natural Language :: English
Classifier: Operating System :: OS Independent
Classifier: Topic :: Software Development :: Testing
Classifier: Topic :: Software Development :: Testing :: Unit
Requires-Python: >=3.8
License-File: COPYING
Requires-Dist: pytest
